m6anet/__init__.py
m6anet/deprecated/__init__.py
m6anet/deprecated/compute_norm_factors.py
m6anet/deprecated/dataprep.py
m6anet/deprecated/inference.py
m6anet/deprecated/train.py
m6anet/model/__init__.py
m6anet/model/model.py
m6anet/model/configs/model_configs/m6anet.toml
m6anet/model/model_blocks/__init__.py
m6anet/model/model_blocks/blocks.py
m6anet/model/model_blocks/pooling_blocks.py
m6anet/model/model_states/rna002_arabidopsis_virc.pt
m6anet/model/model_states/rna002_hct116.pt
m6anet/model/model_states/rna004_hek293t.pt
m6anet/model/norm_factors/rna002_arabidopsis_virc.joblib
m6anet/model/norm_factors/rna002_hct116.joblib
m6anet/scripts/__init__.py
m6anet/scripts/compute_norm_factors.py
m6anet/scripts/convert.py
m6anet/scripts/dataprep.py
m6anet/scripts/inference.py
m6anet/scripts/train.py
m6anet/utils/__init__.py
m6anet/utils/builder.py
m6anet/utils/constants.py
m6anet/utils/data_utils.py
m6anet/utils/dataprep_utils.py
m6anet/utils/helper.py
m6anet/utils/inference_utils.py
m6anet/utils/norm_utils.py
m6anet/utils/sampler_utils.py
m6anet/utils/training_utils.py
m6anet/utils/loss_functions/__init__.py
m6anet/utils/loss_functions/loss_functions.py
m6anet-2.1.0.dist-info/LICENSE
m6anet-2.1.0.dist-info/METADATA
m6anet-2.1.0.dist-info/WHEEL
m6anet-2.1.0.dist-info/entry_points.txt
m6anet-2.1.0.dist-info/top_level.txt
m6anet-2.1.0.dist-info/RECORD
