Metadata-Version: 2.1
Name: m6anet
Version: 2.1.0
Summary: m6anet is a python package for detection of m6a modifications from Nanopore direct RNA sequencing data.
Home-page: https://github.com/GoekeLab/m6anet
Author: Christopher Hendra
Maintainer-email: christopher.hendra@u.nus.edu
License: MIT
Classifier: Development Status :: 1 - Planning
Classifier: License :: OSI Approved :: MIT License
Classifier: Programming Language :: Python
Classifier: Programming Language :: Python :: 3.7
Classifier: Topic :: Software Development :: Libraries
Classifier: Topic :: Scientific/Engineering :: Bio-Informatics
Classifier: Intended Audience :: Science/Research
Requires-Python: >=3.7, <3.9
License-File: LICENSE
Requires-Dist: numpy (>=1.18.0)
Requires-Dist: pandas (>=0.25.3)
Requires-Dist: ujson
Requires-Dist: torch (==1.6.0)
Requires-Dist: toml (>=0.10.2)
Requires-Dist: tqdm
Requires-Dist: typing-extensions
Requires-Dist: scikit-learn (<1.1.0,>=0.24.0) ; python_version == "3.7"
Requires-Dist: scipy (<1.8.0,>=1.4.1) ; python_version == "3.7"
Requires-Dist: scikit-learn (>=0.24.0) ; python_version == "3.8"
Requires-Dist: scipy (>=1.4.1) ; python_version == "3.8"
